setup.py
distributions_mg_1/Binomialdistribution.py
distributions_mg_1/Gaussiandistribution.py
distributions_mg_1/Generaldistribution.py
distributions_mg_1/__init__.py
distributions_mg_1.egg-info/PKG-INFO
distributions_mg_1.egg-info/SOURCES.txt
distributions_mg_1.egg-info/dependency_links.txt
distributions_mg_1.egg-info/not-zip-safe
distributions_mg_1.egg-info/top_level.txt