Metadata-Version: 1.0
Name: distributions-mg-1
Version: 0.1
Summary: Gaussian distributions
Home-page: UNKNOWN
Author: Matthew Gray
Author-email: UNKNOWN
License: UNKNOWN
Platform: UNKNOWN
